sccoda/__init__.py
sccoda/datasets/__init__.py
sccoda/datasets/_datasets.py
sccoda/model/__init__.py
sccoda/model/other_models.py
sccoda/model/scCODA_model.py
sccoda/util/__init__.py
sccoda/util/cell_composition_data.py
sccoda/util/comp_ana.py
sccoda/util/data_generation.py
sccoda/util/data_visualization.py
sccoda/util/helper_functions.py
sccoda/util/result_classes.py
scCODA-0.1.9.dist-info/LICENSE
scCODA-0.1.9.dist-info/METADATA
scCODA-0.1.9.dist-info/WHEEL
scCODA-0.1.9.dist-info/top_level.txt
scCODA-0.1.9.dist-info/RECORD
