Metadata-Version: 2.1
Name: scCODA
Version: 0.1.9
Summary: A Dirichlet-Multinomial approach to identify compositional changes in count data.
Home-page: https://github.com/theislab/scCODA
Author: Johannes Ostner, Benjamin Schubert
Author-email: johannes.ostner@helmholtz-muenchen.de
License: BSD
Keywords: RNA,single cell,composition,CODA,compositional analysis
Classifier: License :: OSI Approved :: BSD License
Classifier: Intended Audience :: Science/Research
Classifier: Programming Language :: Python
Classifier: Programming Language :: Python :: 3
Classifier: Programming Language :: Python :: 3.7
Classifier: Topic :: Scientific/Engineering :: Bio-Informatics
Requires-Python: >=3.7.0
License-File: LICENSE
Requires-Dist: numpy (>=1.21)
Requires-Dist: scipy
Requires-Dist: tensorflow (>=2.8)
Requires-Dist: tensorflow-probability (>=0.16.0)
Requires-Dist: arviz (>=0.11)
Requires-Dist: seaborn
Requires-Dist: pandas (>=1.0)
Requires-Dist: matplotlib (>=3.0)
Requires-Dist: scanpy
Requires-Dist: anndata
Requires-Dist: patsy
Requires-Dist: statsmodels
Requires-Dist: rpy2
